rdworks/__init__.py
rdworks/cluster/autograph/README
rdworks/cluster/autograph/__init__.py
rdworks/cluster/autograph/autograph.py
rdworks/cluster/autograph/centroid.py
rdworks/cluster/autograph/dynamictreecut.py
rdworks/cluster/autograph/nmrclust.py
rdworks/cluster/autograph/rckmeans.py
rdworks/cluster/bitqt/README
rdworks/cluster/bitqt/__init__.py
rdworks/cluster/bitqt/bitqt.py
rdworks/complete.py
rdworks/conf.py
rdworks/data/Asinex_fragment.xml
rdworks/data/Astex_RO3.xml
rdworks/data/Baell2010_PAINS/Baell2010-PAINS-si.pdf
rdworks/data/Baell2010_PAINS/Baell2010-PAINS.pdf
rdworks/data/Baell2010_PAINS/Baell2010A.csv
rdworks/data/Baell2010_PAINS/Baell2010A.xml
rdworks/data/Baell2010_PAINS/Baell2010B.csv
rdworks/data/Baell2010_PAINS/Baell2010B.xml
rdworks/data/Baell2010_PAINS/Baell2010C.csv
rdworks/data/Baell2010_PAINS/Baell2010C.xml
rdworks/data/Baell2010_PAINS/PAINS-less-than-015-hits.ism
rdworks/data/Baell2010_PAINS/PAINS-less-than-015-hits.xml
rdworks/data/Baell2010_PAINS/PAINS-less-than-150-hits.ism
rdworks/data/Baell2010_PAINS/PAINS-less-than-150-hits.xml
rdworks/data/Baell2010_PAINS/PAINS-more-than-150-hits.ism
rdworks/data/Baell2010_PAINS/PAINS-more-than-150-hits.xml
rdworks/data/Baell2010_PAINS/makexml.py
rdworks/data/Brenk2008_Dundee/Brenk2008.csv
rdworks/data/Brenk2008_Dundee/Brenk2008.xml
rdworks/data/Brenk2008_Dundee/Brenk_et_al-2008-ChemMedChem-SI.pdf
rdworks/data/Brenk2008_Dundee/Brenk_et_al-2008-ChemMedChem-SI.txt
rdworks/data/Brenk2008_Dundee/Brenk_et_al-2008-ChemMedChem.pdf
rdworks/data/Brenk2008_Dundee/makexml.py
rdworks/data/CNS.xml
rdworks/data/ChEMBL_Walters/BMS.xml
rdworks/data/ChEMBL_Walters/Dundee.xml
rdworks/data/ChEMBL_Walters/Glaxo.xml
rdworks/data/ChEMBL_Walters/Inpharmatica.xml
rdworks/data/ChEMBL_Walters/LINT.xml
rdworks/data/ChEMBL_Walters/MLSMR.xml
rdworks/data/ChEMBL_Walters/PAINS.xml
rdworks/data/ChEMBL_Walters/README
rdworks/data/ChEMBL_Walters/SureChEMBL.xml
rdworks/data/ChEMBL_Walters/alert_collection.csv
rdworks-0.74.1.dist-info/WHEEL
rdworks-0.74.1.dist-info/METADATA
rdworks-0.74.1.dist-info/RECORD
