Metadata-Version: 2.3
Name: rdworks
Version: 0.74.1
Summary: Chained Workflow built on RDKit
Author: SungHun Bae
Author-email: SungHun Bae <sunghun.bae@gmail.com>
Requires-Dist: ase>=3.26.0
Requires-Dist: bitarray>=3.8.0
Requires-Dist: cdpkit>=1.2.3
Requires-Dist: networkx>=3.6.1
Requires-Dist: numpy>=2.3.5
Requires-Dist: pandas>=2.3.3
Requires-Dist: pillow>=12.0.0
Requires-Dist: rdkit>=2025.9.3
Requires-Dist: scipy>=1.16.3
Requires-Dist: scour>=0.38.2
Requires-Dist: spyrmsd>=0.9.0
Requires-Dist: tqdm>=4.67.1
Requires-Python: >=3.12
Project-URL: Changelog, https://github.com/sunghunbae/rdworks/blob/master/CHANGELOG.md
Project-URL: Documentation, https://sunghunbae.github.io/rdworks/
Project-URL: Homepage, https://github.com/sunghunbae/rdworks
Project-URL: Issues, https://github.com/sunghunbae/rdworks/issues
Project-URL: Repository, https://github.com/sunghunbae/rdworks.git
